usfm2dict/__init__.py
usfm2dict/__main__.py
usfm2dict/canon.py
usfm2dict/cli.py
usfm2dict/models.py
usfm2dict/parser.py
usfm2dict/stylesheet.py
usfm2dict/tokenizer.py
usfm2dict-0.1.3.dist-info/licenses/LICENSE
usfm2dict-0.1.3.dist-info/METADATA
usfm2dict-0.1.3.dist-info/WHEEL
usfm2dict-0.1.3.dist-info/entry_points.txt
usfm2dict-0.1.3.dist-info/top_level.txt
usfm2dict-0.1.3.dist-info/RECORD
