Metadata-Version: 2.4
Name: usfm2dict
Version: 0.1.3
Summary: USFM to Dictionary Converter
Home-page: https://github.com/jcuenod/usfm2dict
Author: James Cuénod
Author-email: 4253884+jcuenod@users.noreply.github.com
Classifier: Programming Language :: Python :: 3
Classifier: License :: OSI Approved :: MIT License
Classifier: Operating System :: OS Independent
Requires-Python: >=3.6
License-File: LICENSE
Requires-Dist: regex
Dynamic: license-file
